pythontrie/__init__.py
pythontrie/core.py
pythontrie-0.3.dist-info/LICENSE
pythontrie-0.3.dist-info/METADATA
pythontrie-0.3.dist-info/WHEEL
pythontrie-0.3.dist-info/top_level.txt
pythontrie-0.3.dist-info/RECORD
