Metadata-Version: 2.1
Name: pythontrie
Version: 0.3
Summary: General Purpose Trie Data Structure in Python
Home-page: https://github.com/pranavgupta1234/pythontrie
Author: Pranav Gupta
Author-email: pranavgupta4321@gmail.com
License: Apache Software License
Platform: UNKNOWN
Classifier: Intended Audience :: Developers
Classifier: Topic :: Software Development :: Build Tools
Classifier: License :: OSI Approved :: Apache Software License
Classifier: Programming Language :: Python :: 3.6
Classifier: Programming Language :: Python :: 3.7
